{
  "id": "steuer-dlhv-deutscher-lohnsteuerhilfeverein-e-v",
  "name": "DLHV Deutscher Lohnsteuerhilfeverein e.V.",
  "industry": "Kanzlei",
  "website": "https://www.d-lhv.de/",
  "phone": "+49 381 3750724",
  "email": "rostock@d-lhv.de",
  "address": "Timmermannsstrat 7, 18055 Rostock",
  "city": "Rostock",
  "problems": [
    "Kein Kontaktformular"
  ],
  "opps": [],
  "lighthouse": null,
  "images": [
    "https://www.d-lhv.de/img/steuerbescheid-pruefen.jpg",
    "https://www.d-lhv.de/img/geld-wachstum.jpg",
    "https://www.d-lhv.de/img/erholen-sie-sich.jpg",
    "https://www.d-lhv.de/img/entspannen-sie-sich.jpg"
  ],
  "content": {
    "title": "DLHV einfach beraten - Start",
    "desc": "Deutscher Lohnsteuerhilfeverein e.V. Mitglied werden und die Steuern sind erledigt.",
    "h1": [
      "Deutscher Lohnsteuerhilfeverein e.V."
    ],
    "h2": [
      "Machen Sie, was Sie wollen...Ihre Steuern machen wir.",
      "Deutscher Lohnsteuerhilfeverein e.V.",
      "Machen Sie, was Sie wollen... Ihre Steuern erledigen wir für Sie.",
      "Nutzen Sie jetzt alle Vorteile",
      "Kooperationspartner"
    ]
  },
  "status": "published",
  "createdAt": "2026-06-20T16:57:23.323Z",
  "publishedAt": "2026-06-20T17:27:54.129Z"
}