{
  "id": "kfz-euromaster",
  "name": "Euromaster",
  "industry": "Dienstleistung",
  "website": "https://www.euromaster.de/filiale/bayern/muenchen/yudqvtk-euromaster-muenchen",
  "phone": "+49 89 8682825",
  "email": "de743usr01@euromaster.com",
  "address": "Aschauer Straße 6, 81549 München",
  "city": "München",
  "problems": [],
  "opps": [],
  "lighthouse": null,
  "images": [
    "https://www.euromaster.de/upload/euromaster_eshop/promoBanner/de_DE/beste-aktionen-grafik-doofinder.jpg",
    "https://www.euromaster.de/v/3.26.5.0.16/34168219/img/store/euromaster_eshop/tyreseletor-full.png",
    "https://www.euromaster.de/upload/euromaster_eshop/img/de_DE/image-hsntsn.png"
  ],
  "content": {
    "title": "Auto-Werkstatt München - Euromaster, Ihr Auto-Experte - EUROMASTER München PKW",
    "desc": "Kompetente Reparatur & Wartung bei Euromaster in München : TÜV-Abnahme, Inspektion und alles rund ums Auto vom Reifen- bis zum Ölwechsel!",
    "h1": [
      "EUROMASTER München PKW"
    ],
    "h2": [
      "Fahrzeugtypen",
      "Unsere Services",
      "Eine Reihe von Kundeneinrichtungen sind verfügbar"
    ]
  },
  "status": "needs_build",
  "createdAt": "2026-06-20T17:39:22.010Z"
}