{
  "id": "physio-regenaphysiotherapie",
  "name": "RegenaPhysioTherapie",
  "industry": "Physiotherapie",
  "website": "https://www.regenaphysiotherapie.de",
  "phone": "+49 931 354460",
  "email": "info@regenaphysiotherapie.de",
  "address": ", Würzburg",
  "city": "Würzburg",
  "problems": [
    "WordPress (potenziell veraltbar)",
    "Wenig Bildmaterial"
  ],
  "opps": [],
  "lighthouse": null,
  "images": [
    "https://regena-physiotherapie.de/wp-content/uploads/2025/05/dorothea-schirmacher.jpg",
    "https://regenaphysiotherapie.de/wp-content/uploads/2025/05/dorothea-schirmacher.jpg",
    "https://regenaphysiotherapie.de/wp-content/uploads/2025/05/dorothea-schirmacher-150x150.jpg"
  ],
  "content": {
    "title": "Regena Physiotherapie",
    "desc": "",
    "h1": [
      "Start"
    ],
    "h2": [
      "Öffnungszeiten:",
      "Wichtige Stichworte:",
      "Neueste Beiträge",
      "Neueste Kommentare",
      "Archive",
      "Kategorien"
    ]
  },
  "status": "published",
  "createdAt": "2026-06-20T17:39:09.821Z",
  "publishedAt": "2026-06-21T17:24:16.239Z"
}