{
  "id": "sanitaer-hta-haustechnik-atlas",
  "name": "HTA Haustechnik Atlas",
  "industry": "Handwerk",
  "website": "https://heizungswartung-potsdam.de/",
  "phone": "+49 331 885 499763",
  "email": "haustechnik-atlas@gmx.de",
  "address": "Gutenbergstraße 16, 14467 Potsdam",
  "city": "Potsdam",
  "problems": [],
  "opps": [],
  "lighthouse": null,
  "images": [
    "https://heizungswartung-potsdam.de/images/template-content/stoerer.png"
  ],
  "content": {
    "title": "HTA Haustechnik f&#xFC;r Heizungswartung im Raum Potsdam",
    "desc": "HTA Haustechnik Atlas, Ihr Partner f&#xFC;r Heizungswartung in Potsdam. Wartung von Heizungsanlagen, Solaranlagen, &#xDC;berpr&#xFC;fung von Gasleitungen und mehr.",
    "h1": [
      "Ihr Spezialist f&#xFC;r Heizungswartung in Potsdam"
    ],
    "h2": [
      "Solar - B&#xE4;der - Heizung &#x2013; HTA Haustechnik Atlas macht&#x2019;s m&#xF6;glich"
    ]
  },
  "status": "published",
  "createdAt": "2026-06-20T16:57:24.828Z",
  "publishedAt": "2026-06-20T17:24:38.497Z"
}